dvf1312/__init__.py
dvf1312/dvf1312.py
dvf1312-20092023.dist-info/METADATA
dvf1312-20092023.dist-info/WHEEL
dvf1312-20092023.dist-info/licenses/LICENCE
dvf1312-20092023.dist-info/RECORD
