Metadata-Version: 2.1
Name: dvf1312
Version: 20092023
Summary: dvf1312
Project-URL: Homepage, https://gitlab.com/aurelpere/dvf1312
Project-URL: Bug Tracker, https://gitlab.com/aurelpere/dvf1312/issues
Author-email: kr1p <aurel.pere@matangi.dev>
License-File: LICENCE
Classifier: License :: OSI Approved :: Artistic License
Classifier: Operating System :: OS Independent
Classifier: Programming Language :: Python :: 3
Requires-Python: >=3.7
